Metadata-Version: 2.4
Name: databricks-sdk
Version: 0.48.0
Summary: Databricks SDK for Python (Beta)
Project-URL: Documentation, https://databricks-sdk-py.readthedocs.io
Keywords: databricks,sdk
Classifier: Development Status :: 4 - Beta
Classifier: Intended Audience :: Developers
Classifier: Intended Audience :: Science/Research
Classifier: Intended Audience :: System Administrators
Classifier: License :: OSI Approved :: Apache Software License
Classifier: Programming Language :: Python :: 3.7
Classifier: Programming Language :: Python :: 3.8
Classifier: Programming Language :: Python :: 3.9
Classifier: Programming Language :: Python :: 3.10
Classifier: Programming Language :: Python :: 3.11
Classifier: Programming Language :: Python :: 3.12
Classifier: Programming Language :: Python :: 3.13
Classifier: Operating System :: OS Independent
Requires-Python: >=3.7
License-File: LICENSE
License-File: NOTICE
Requires-Dist: requests<3,>=2.28.1
Requires-Dist: google-auth~=2.0
Provides-Extra: dev
Requires-Dist: pytest; extra == "dev"
Requires-Dist: pytest-cov; extra == "dev"
Requires-Dist: pytest-xdist; extra == "dev"
Requires-Dist: pytest-mock; extra == "dev"
Requires-Dist: black; extra == "dev"
Requires-Dist: pycodestyle; extra == "dev"
Requires-Dist: autoflake; extra == "dev"
Requires-Dist: isort; extra == "dev"
Requires-Dist: wheel; extra == "dev"
Requires-Dist: ipython; extra == "dev"
Requires-Dist: ipywidgets; extra == "dev"
Requires-Dist: requests-mock; extra == "dev"
Requires-Dist: pyfakefs; extra == "dev"
Requires-Dist: databricks-connect; extra == "dev"
Requires-Dist: pytest-rerunfailures; extra == "dev"
Requires-Dist: openai; extra == "dev"
Requires-Dist: langchain-openai; python_version > "3.7" and extra == "dev"
Requires-Dist: httpx; extra == "dev"
Requires-Dist: build; extra == "dev"
Provides-Extra: notebook
Requires-Dist: ipython<10,>=8; extra == "notebook"
Requires-Dist: ipywidgets<9,>=8; extra == "notebook"
Provides-Extra: openai
Requires-Dist: openai; extra == "openai"
Requires-Dist: langchain-openai; python_version > "3.7" and extra == "openai"
Requires-Dist: httpx; extra == "openai"
Dynamic: license-file
